app_gui.py
app_predictor.py
download_models.py
voicemd/__init__.py
voicemd/config.yaml
voicemd/config_debug.yaml
voicemd/eval.py
voicemd/main.py
voicemd/predict.py
voicemd/train.py
voicemd/colab/__init__.py
voicemd/colab/clean_uploads.py
voicemd/colab/prediction.py
voicemd/data/__init__.py
voicemd/data/analyze_results.py
voicemd/data/dataloaders.py
voicemd/data/prepare_dataloaders.py
voicemd/data/process_sound.py
voicemd/models/__init__.py
voicemd/models/densenet.py
voicemd/models/long_filter_cnn.py
voicemd/models/model_loader.py
voicemd/models/my_model.py
voicemd/models/simple_cnn.py
voicemd/utils/__init__.py
voicemd/utils/balance_commonvoice_metadata.py
voicemd/utils/extract_cv_subset.py
voicemd/utils/hp_utils.py
voicemd/utils/logging_utils.py
voicemd/utils/preprocess_data.py
voicemd_gui-1.0.2.dist-info/licenses/LICENSE
voicemd_gui-1.0.2.dist-info/METADATA
voicemd_gui-1.0.2.dist-info/WHEEL
voicemd_gui-1.0.2.dist-info/entry_points.txt
voicemd_gui-1.0.2.dist-info/top_level.txt
voicemd_gui-1.0.2.dist-info/RECORD
