Metadata-Version: 2.4
Name: voicemd-gui
Version: 1.0.2
Summary: Modern offline voice analysis application
Home-page: https://github.com/Honey181/voicemd
Author: Honey181
Author-email: 
License: MIT
Project-URL: Homepage, https://github.com/Honey181/voicemd
Project-URL: Repository, https://github.com/Honey181/voicemd
Project-URL: Issues, https://github.com/Honey181/voicemd/issues
Keywords: voice,analysis,audio,machine-learning,pytorch
Classifier: Development Status :: 4 - Beta
Classifier: Intended Audience :: Science/Research
Classifier: License :: OSI Approved :: MIT License
Classifier: Programming Language :: Python :: 3
Classifier: Programming Language :: Python :: 3.8
Classifier: Programming Language :: Python :: 3.9
Classifier: Programming Language :: Python :: 3.10
Classifier: Programming Language :: Python :: 3.11
Classifier: Programming Language :: Python :: 3.12
Classifier: Programming Language :: Python :: 3.13
Classifier: Topic :: Scientific/Engineering :: Artificial Intelligence
Requires-Python: >=3.8,<3.14
License-File: LICENSE
Requires-Dist: torch>=1.13.0
Requires-Dist: torchaudio>=0.13.0
Requires-Dist: torchvision>=0.15.0
Requires-Dist: numpy>=1.21.0
Requires-Dist: librosa>=0.10.0
Requires-Dist: soundfile>=0.12.0
Requires-Dist: scipy>=1.9.0
Requires-Dist: PyYAML>=6.0
Requires-Dist: requests>=2.28.0
Dynamic: home-page
Dynamic: license-file
Dynamic: requires-python
